mixdq_extension/_C.cpython-39-x86_64-linux-gnu.so
mixdq_extension/__init__.py
mixdq_extension-0.6.dist-info/METADATA
mixdq_extension-0.6.dist-info/WHEEL
mixdq_extension-0.6.dist-info/top_level.txt
mixdq_extension-0.6.dist-info/RECORD
