Metadata-Version: 2.1
Name: mixdq-extension
Version: 0.6
Requires-Python: >=3.7
Requires-Dist: diffusers ==0.26.3
Requires-Dist: peft ==0.9.0
Requires-Dist: torch ==2.2.1
Requires-Dist: torchvision ==0.17.1
Requires-Dist: transformers ==4.38.2
Requires-Dist: pytorch-lightning ==2.2.3
